{
  "skills": {
    "categories": [
      {
        "id": "intellect",
        "name": "Intelecto & Ciencia",
        "icon": "Brain",
        "color": "hsl(185, 100%, 50%)",
        "level": 0,
        "children": [
          {
            "id": "physics",
            "name": "Fisica",
            "level": 0,
            "xpRequired": 1000,
            "xpCurrent": 0,
            "children": [],
            "parentId": null
          },
          {
            "id": "math",
            "name": "Matematicas",
            "level": 0,
            "xpRequired": 1000,
            "xpCurrent": 0,
            "children": [],
            "parentId": null
          },
          {
            "id": "programming",
            "name": "Programacion",
            "level": 0,
            "xpRequired": 1000,
            "xpCurrent": 0,
            "parentId": null,
            "children": [
              {
                "id": "frontend",
                "name": "Frontend",
                "level": 0,
                "xpRequired": 1000,
                "xpCurrent": 0,
                "children": [],
                "parentId": "programming"
              },
              {
                "id": "backend",
                "name": "Backend",
                "level": 0,
                "xpRequired": 1000,
                "xpCurrent": 0,
                "children": [],
                "parentId": "programming"
              },
              {
                "id": "devops",
                "name": "DevOps",
                "level": 0,
                "xpRequired": 1000,
                "xpCurrent": 0,
                "children": [],
                "parentId": "programming"
              }
            ]
          },
          {
            "id": "networking",
            "name": "Redes",
            "level": 0,
            "xpRequired": 1000,
            "xpCurrent": 0,
            "children": [],
            "parentId": null
          },
          {
            "id": "ai",
            "name": "IA & ML",
            "level": 0,
            "xpRequired": 1000,
            "xpCurrent": 0,
            "children": [],
            "parentId": null
          }
        ]
      },
      {
        "id": "wellness",
        "name": "Bienestar & Salud",
        "icon": "Heart",
        "color": "hsl(300, 100%, 50%)",
        "level": 0,
        "children": [
          {
            "id": "health",
            "name": "Salud General",
            "level": 0,
            "xpRequired": 1000,
            "xpCurrent": 0,
            "children": [],
            "parentId": null
          },
          {
            "id": "exercise",
            "name": "Ejercicio",
            "level": 0,
            "xpRequired": 1000,
            "xpCurrent": 0,
            "children": [],
            "parentId": null
          },
          {
            "id": "nutrition",
            "name": "Nutricion",
            "level": 0,
            "xpRequired": 1000,
            "xpCurrent": 0,
            "children": [],
            "parentId": null
          },
          {
            "id": "meditation",
            "name": "Meditacion",
            "level": 0,
            "xpRequired": 1000,
            "xpCurrent": 0,
            "children": [],
            "parentId": null
          },
          {
            "id": "sleep",
            "name": "Sueno",
            "level": 0,
            "xpRequired": 1000,
            "xpCurrent": 0,
            "children": [],
            "parentId": null
          }
        ]
      },
      {
        "id": "humanities",
        "name": "Humanidades & Sociedad",
        "icon": "BookOpen",
        "color": "hsl(82, 100%, 55%)",
        "level": 0,
        "children": [
          {
            "id": "sociology",
            "name": "Sociologia",
            "level": 0,
            "xpRequired": 1000,
            "xpCurrent": 0,
            "children": [],
            "parentId": null
          },
          {
            "id": "history",
            "name": "Historia",
            "level": 0,
            "xpRequired": 1000,
            "xpCurrent": 0,
            "children": [],
            "parentId": null
          },
          {
            "id": "philosophy",
            "name": "Filosofia",
            "level": 0,
            "xpRequired": 1000,
            "xpCurrent": 0,
            "children": [],
            "parentId": null
          },
          {
            "id": "languages",
            "name": "Bilingue",
            "level": 0,
            "xpRequired": 1000,
            "xpCurrent": 0,
            "children": [],
            "parentId": null
          },
          {
            "id": "communication",
            "name": "Comunicacion",
            "level": 0,
            "xpRequired": 1000,
            "xpCurrent": 0,
            "children": [],
            "parentId": null
          }
        ]
      },
      {
        "id": "creativity",
        "name": "Creatividad & Arte",
        "icon": "Palette",
        "color": "hsl(35, 100%, 55%)",
        "level": 1,
        "children": [
          {
            "id": "visual-art",
            "name": "Arte Visual",
            "level": 2,
            "xpRequired": 1000,
            "xpCurrent": 15,
            "children": [],
            "parentId": null
          },
          {
            "id": "music",
            "name": "Musica",
            "level": 0,
            "xpRequired": 1000,
            "xpCurrent": 0,
            "children": [],
            "parentId": null
          },
          {
            "id": "design",
            "name": "Diseno",
            "level": 0,
            "xpRequired": 1000,
            "xpCurrent": 0,
            "children": [],
            "parentId": null
          },
          {
            "id": "writing",
            "name": "Escritura",
            "level": 0,
            "xpRequired": 1000,
            "xpCurrent": 0,
            "children": [],
            "parentId": null
          }
        ]
      },
      {
        "id": "personal",
        "name": "Desarrollo Personal",
        "icon": "Target",
        "color": "hsl(55, 100%, 55%)",
        "level": 0,
        "children": [
          {
            "id": "responsibility",
            "name": "Responsabilidad",
            "level": 0,
            "xpRequired": 1000,
            "xpCurrent": 0,
            "children": [],
            "parentId": null
          },
          {
            "id": "discipline",
            "name": "Disciplina",
            "level": 0,
            "xpRequired": 1000,
            "xpCurrent": 0,
            "children": [],
            "parentId": null
          },
          {
            "id": "productivity",
            "name": "Productividad",
            "level": 0,
            "xpRequired": 1000,
            "xpCurrent": 0,
            "children": [],
            "parentId": null
          },
          {
            "id": "leadership",
            "name": "Liderazgo",
            "level": 0,
            "xpRequired": 1000,
            "xpCurrent": 0,
            "children": [],
            "parentId": null
          }
        ]
      },
      {
        "id": "finance",
        "name": "Finanzas & Exito",
        "icon": "TrendingUp",
        "color": "hsl(220, 100%, 60%)",
        "level": 0,
        "children": [
          {
            "id": "savings",
            "name": "Ahorro",
            "level": 0,
            "xpRequired": 1000,
            "xpCurrent": 0,
            "children": [],
            "parentId": null
          },
          {
            "id": "investments",
            "name": "Inversiones",
            "level": 0,
            "xpRequired": 1000,
            "xpCurrent": 0,
            "children": [],
            "parentId": null
          },
          {
            "id": "business",
            "name": "Negocios",
            "level": 0,
            "xpRequired": 1000,
            "xpCurrent": 0,
            "children": [],
            "parentId": null
          },
          {
            "id": "income",
            "name": "Ingresos",
            "level": 0,
            "xpRequired": 1000,
            "xpCurrent": 0,
            "children": [],
            "parentId": null
          }
        ]
      }
    ],
    "overallLevel": 0
  },
  "tasks": [
    {
      "id": "c475a5f9-462c-44c8-9d29-1d96d2047768",
      "description": "",
      "frequency": "daily",
      "priority": "medium",
      "status": "completed",
      "validationRule": "manual-confirm",
      "xpReward": 15,
      "createdAt": "2026-03-08T05:10:54.292Z",
      "tags": [],
      "streak": 1,
      "title": "Pintar ",
      "skillCategoryId": "creativity",
      "subSkillId": "visual-art",
      "completedAt": "2026-03-08T05:10:56.049Z"
    }
  ],
  "goals": [],
  "user": {
    "id": "user-1",
    "nickname": "CyberRunner",
    "avatarUrl": null,
    "level": 1,
    "totalXp": 15,
    "joinedAt": "2026-01-01T00:00:00.000Z",
    "currentStreak": 1,
    "longestStreak": 1
  },
  "settings": {
    "theme": "cyberpunk",
    "notificationsEnabled": true,
    "dailyReminderTime": "08:00",
    "strictValidation": true,
    "language": "es"
  },
  "accounts": [
    {
      "id": "arelyxl",
      "pinHash": "$2a$10$KTUIGP/n4upO/SCbnBo.YOsuvlinKUm5aRD0qEm290niTcdOFw7pG",
      "state": {
        "skills": {
          "categories": [
            {
              "id": "intellect",
              "name": "Intelecto & Ciencia",
              "icon": "Brain",
              "color": "hsl(185, 100%, 50%)",
              "level": 1,
              "children": [
                {
                  "id": "physics",
                  "name": "Fisica",
                  "level": 0,
                  "xpRequired": 1000,
                  "xpCurrent": 0,
                  "children": [],
                  "parentId": null
                },
                {
                  "id": "math",
                  "name": "Matematicas",
                  "level": 10,
                  "xpRequired": 1000,
                  "xpCurrent": 0,
                  "children": [
                    {
                      "id": "trans-7f07a008-15ce-4a56-b390-dba34ed70388",
                      "name": "Matematicas — General",
                      "level": 0,
                      "xpRequired": 1000,
                      "xpCurrent": 50,
                      "children": [],
                      "parentId": "math"
                    },
                    {
                      "id": "00a835b7-93e3-440a-84b9-5dad2181c527",
                      "name": "Estadistica",
                      "level": 5,
                      "xpRequired": 1000,
                      "xpCurrent": 50,
                      "children": [],
                      "parentId": "math"
                    }
                  ],
                  "parentId": null
                },
                {
                  "id": "programming",
                  "name": "Programacion",
                  "level": 0,
                  "xpRequired": 1000,
                  "xpCurrent": 0,
                  "parentId": null,
                  "children": [
                    {
                      "id": "frontend",
                      "name": "Frontend",
                      "level": 0,
                      "xpRequired": 1000,
                      "xpCurrent": 0,
                      "children": [],
                      "parentId": "programming"
                    },
                    {
                      "id": "backend",
                      "name": "Backend",
                      "level": 0,
                      "xpRequired": 1000,
                      "xpCurrent": 0,
                      "children": [],
                      "parentId": "programming"
                    },
                    {
                      "id": "devops",
                      "name": "DevOps",
                      "level": 0,
                      "xpRequired": 1000,
                      "xpCurrent": 0,
                      "children": [],
                      "parentId": "programming"
                    }
                  ]
                },
                {
                  "id": "networking",
                  "name": "Redes",
                  "level": 0,
                  "xpRequired": 1000,
                  "xpCurrent": 0,
                  "children": [],
                  "parentId": null
                },
                {
                  "id": "ai",
                  "name": "IA & ML",
                  "level": 0,
                  "xpRequired": 1000,
                  "xpCurrent": 0,
                  "children": [],
                  "parentId": null
                }
              ]
            },
            {
              "id": "wellness",
              "name": "Bienestar & Salud",
              "icon": "Heart",
              "color": "hsl(300, 100%, 50%)",
              "level": 0,
              "children": [
                {
                  "id": "health",
                  "name": "Salud General",
                  "level": 0,
                  "xpRequired": 1000,
                  "xpCurrent": 0,
                  "children": [],
                  "parentId": null
                },
                {
                  "id": "exercise",
                  "name": "Ejercicio",
                  "level": 0,
                  "xpRequired": 1000,
                  "xpCurrent": 0,
                  "children": [],
                  "parentId": null
                },
                {
                  "id": "nutrition",
                  "name": "Nutricion",
                  "level": 0,
                  "xpRequired": 1000,
                  "xpCurrent": 0,
                  "children": [],
                  "parentId": null
                },
                {
                  "id": "meditation",
                  "name": "Meditacion",
                  "level": 0,
                  "xpRequired": 1000,
                  "xpCurrent": 0,
                  "children": [],
                  "parentId": null
                },
                {
                  "id": "sleep",
                  "name": "Sueno",
                  "level": 0,
                  "xpRequired": 1000,
                  "xpCurrent": 0,
                  "children": [],
                  "parentId": null
                }
              ]
            },
            {
              "id": "humanities",
              "name": "Humanidades & Sociedad",
              "icon": "BookOpen",
              "color": "hsl(82, 100%, 55%)",
              "level": 0,
              "children": [
                {
                  "id": "sociology",
                  "name": "Sociologia",
                  "level": 0,
                  "xpRequired": 1000,
                  "xpCurrent": 0,
                  "children": [],
                  "parentId": null
                },
                {
                  "id": "history",
                  "name": "Historia",
                  "level": 0,
                  "xpRequired": 1000,
                  "xpCurrent": 0,
                  "children": [],
                  "parentId": null
                },
                {
                  "id": "philosophy",
                  "name": "Filosofia",
                  "level": 0,
                  "xpRequired": 1000,
                  "xpCurrent": 0,
                  "children": [],
                  "parentId": null
                },
                {
                  "id": "languages",
                  "name": "Bilingue",
                  "level": 0,
                  "xpRequired": 1000,
                  "xpCurrent": 0,
                  "children": [],
                  "parentId": null
                },
                {
                  "id": "communication",
                  "name": "Comunicacion",
                  "level": 0,
                  "xpRequired": 1000,
                  "xpCurrent": 0,
                  "children": [],
                  "parentId": null
                }
              ]
            },
            {
              "id": "creativity",
              "name": "Creatividad & Arte",
              "icon": "Palette",
              "color": "hsl(35, 100%, 55%)",
              "level": 0,
              "children": [
                {
                  "id": "visual-art",
                  "name": "Arte Visual",
                  "level": 0,
                  "xpRequired": 1000,
                  "xpCurrent": 0,
                  "children": [
                    {
                      "id": "cfd73170-1fc2-4f6c-8a37-861f576001b0",
                      "name": "Acuarelas",
                      "level": 0,
                      "xpRequired": 1000,
                      "xpCurrent": 0,
                      "children": [],
                      "parentId": "visual-art"
                    },
                    {
                      "id": "2763c4b5-418c-48c3-8753-ffeb41fe10f8",
                      "name": "Dibujo",
                      "level": 2,
                      "xpRequired": 1000,
                      "xpCurrent": 0,
                      "children": [
                        {
                          "id": "trans-0e9099eb-6895-45e8-8cbd-9f29cccf8ed3",
                          "name": "Dibujo — General",
                          "level": 0,
                          "xpRequired": 1000,
                          "xpCurrent": 0,
                          "children": [],
                          "parentId": "2763c4b5-418c-48c3-8753-ffeb41fe10f8"
                        },
                        {
                          "id": "e6b4af4e-5228-475c-bf7f-3b4e474eafbb",
                          "name": "Anatomia",
                          "level": 2,
                          "xpRequired": 1000,
                          "xpCurrent": 15,
                          "children": [],
                          "parentId": "2763c4b5-418c-48c3-8753-ffeb41fe10f8"
                        }
                      ],
                      "parentId": "visual-art"
                    }
                  ],
                  "parentId": null
                },
                {
                  "id": "music",
                  "name": "Musica",
                  "level": 0,
                  "xpRequired": 1000,
                  "xpCurrent": 0,
                  "children": [],
                  "parentId": null
                },
                {
                  "id": "design",
                  "name": "Diseno",
                  "level": 0,
                  "xpRequired": 1000,
                  "xpCurrent": 0,
                  "children": [],
                  "parentId": null
                },
                {
                  "id": "writing",
                  "name": "Escritura",
                  "level": 0,
                  "xpRequired": 1000,
                  "xpCurrent": 0,
                  "children": [],
                  "parentId": null
                }
              ]
            },
            {
              "id": "personal",
              "name": "Desarrollo Personal",
              "icon": "Target",
              "color": "hsl(55, 100%, 55%)",
              "level": 0,
              "children": [
                {
                  "id": "responsibility",
                  "name": "Responsabilidad",
                  "level": 0,
                  "xpRequired": 1000,
                  "xpCurrent": 0,
                  "children": [],
                  "parentId": null
                },
                {
                  "id": "discipline",
                  "name": "Disciplina",
                  "level": 0,
                  "xpRequired": 1000,
                  "xpCurrent": 0,
                  "children": [],
                  "parentId": null
                },
                {
                  "id": "productivity",
                  "name": "Productividad",
                  "level": 0,
                  "xpRequired": 1000,
                  "xpCurrent": 0,
                  "children": [],
                  "parentId": null
                },
                {
                  "id": "leadership",
                  "name": "Liderazgo",
                  "level": 0,
                  "xpRequired": 1000,
                  "xpCurrent": 0,
                  "children": [],
                  "parentId": null
                }
              ]
            },
            {
              "id": "finance",
              "name": "Finanzas & Exito",
              "icon": "TrendingUp",
              "color": "hsl(220, 100%, 60%)",
              "level": 0,
              "children": [
                {
                  "id": "savings",
                  "name": "Ahorro",
                  "level": 0,
                  "xpRequired": 1000,
                  "xpCurrent": 0,
                  "children": [],
                  "parentId": null
                },
                {
                  "id": "investments",
                  "name": "Inversiones",
                  "level": 0,
                  "xpRequired": 1000,
                  "xpCurrent": 0,
                  "children": [],
                  "parentId": null
                },
                {
                  "id": "business",
                  "name": "Negocios",
                  "level": 0,
                  "xpRequired": 1000,
                  "xpCurrent": 0,
                  "children": [],
                  "parentId": null
                },
                {
                  "id": "income",
                  "name": "Ingresos",
                  "level": 0,
                  "xpRequired": 1000,
                  "xpCurrent": 0,
                  "children": [],
                  "parentId": null
                }
              ]
            }
          ],
          "overallLevel": 0
        },
        "tasks": [
          {
            "id": "32a1ceca-6760-437e-ae65-98d14b6f9329",
            "description": "Pintar con acuarelas mi portada como stickers",
            "frequency": "one-time",
            "priority": "medium",
            "status": "pending",
            "validationRule": "manual-confirm",
            "xpReward": 15,
            "createdAt": "2026-03-08T13:44:52.409Z",
            "tags": [
              "arte",
              "pintura"
            ],
            "streak": 0,
            "title": "Pintar la caratula de mi sketch",
            "skillCategoryId": "creativity",
            "subSkillId": "cfd73170-1fc2-4f6c-8a37-861f576001b0",
            "dueDate": "2026-03-08"
          },
          {
            "id": "504b8f68-3881-41f1-a17d-8cab7f8e5f5e",
            "description": "",
            "frequency": "daily",
            "priority": "medium",
            "status": "completed",
            "validationRule": "manual-confirm",
            "xpReward": 15,
            "createdAt": "2026-03-10T17:19:57.871Z",
            "tags": [],
            "streak": 1,
            "title": "Dibujar Logo",
            "skillCategoryId": "creativity",
            "subSkillId": "2763c4b5-418c-48c3-8753-ffeb41fe10f8",
            "completedAt": "2026-03-10T17:20:00.286Z"
          }
        ],
        "goals": [],
        "user": {
          "id": "user-1",
          "nickname": "ArelyXl",
          "avatarUrl": null,
          "level": 1,
          "totalXp": 115,
          "joinedAt": "2026-01-01T00:00:00.000Z",
          "currentStreak": 2,
          "longestStreak": 2
        },
        "settings": {
          "theme": "cyberpunk",
          "notificationsEnabled": true,
          "dailyReminderTime": "08:00",
          "strictValidation": true,
          "language": "es"
        }
      },
      "pin": "9021"
    },
    {
      "id": "testuser-1772942631",
      "pinHash": "$2a$10$0dhl1ViCIWNzkHmbQqO3GOUSKT3KPzeCnRGbABH8MbZed18u/s0Ya",
      "state": {
        "skills": [],
        "tasks": [],
        "goals": [],
        "user": {
          "id": "user-1",
          "name": "Test User",
          "avatar": "🚀",
          "totalXp": 100,
          "currentLevel": 1,
          "currentStreak": 5,
          "longestStreak": 10
        },
        "settings": {
          "theme": "dark",
          "notifications": true,
          "lang": "es"
        }
      }
    },
    {
      "id": "test-1772942661",
      "pinHash": "$2a$10$bvXQQn4EVfrVSVNzowgbDuLNvom16dwZri/CXkTqqN.X/zhTOobxK",
      "state": {
        "skills": [],
        "tasks": [
          {
            "id": "task1",
            "title": "Test"
          }
        ],
        "goals": [],
        "user": {
          "id": "u1",
          "totalXp": 777
        },
        "settings": {}
      }
    },
    {
      "id": "workflow-test-1772942750",
      "pinHash": "$2a$10$B5Z9WK/lii0sPrQlqeC8Jej5AyRDsnQRaB.1bCiBgxeLUF31U02YW",
      "state": {
        "skills": [
          {
            "id": "skill1",
            "name": "Test Skill",
            "level": 1,
            "xpCurrent": 550,
            "xpRequired": 1000
          }
        ],
        "tasks": [
          {
            "id": "task1",
            "title": "Test Task",
            "status": "completed",
            "skillCategoryId": "category1",
            "completedAt": "2026-03-07"
          }
        ],
        "goals": [],
        "user": {
          "id": "user1",
          "name": "Test User",
          "totalXp": 550,
          "currentLevel": 1,
          "currentStreak": 1
        },
        "settings": {}
      }
    },
    {
      "id": "diag-1772942763",
      "pinHash": "$2a$10$OvHrTmr/mu4xj06/.YqO8.ie9mbGRjeZaC6FKnY5iLoBjWK0Plz02",
      "state": {
        "skills": [],
        "tasks": [
          {
            "id": "t1",
            "title": "Important",
            "status": "pending"
          }
        ],
        "goals": [],
        "user": {
          "id": "u1",
          "totalXp": 999
        },
        "settings": {}
      }
    },
    {
      "id": "final-test-1772942886-18084",
      "pinHash": "$2a$10$oaxLhLjf4vVmXJ3xB5ZrtODwbOCdolCFVO5Ljsm2xvL53H2k8hAl2",
      "state": {
        "skills": [
          {
            "id": "intellect",
            "name": "Intelecto",
            "level": 1,
            "xpCurrent": 750,
            "xpRequired": 1000,
            "color": "hsl(185,100%,50%)"
          }
        ],
        "tasks": [
          {
            "id": "t1",
            "title": "Task 1",
            "status": "completed",
            "completedAt": "2026-03-07"
          },
          {
            "id": "t2",
            "title": "Task 2",
            "status": "completed"
          },
          {
            "id": "t3",
            "title": "Task 3",
            "status": "completed",
            "completedAt": "2026-03-07"
          },
          {
            "id": "t4",
            "title": "New Task",
            "status": "pending"
          }
        ],
        "goals": [
          {
            "id": "g1",
            "title": "Goal 1",
            "targetDays": 30,
            "entries": [
              {
                "date": "2026-03-07",
                "completed": true
              }
            ]
          }
        ],
        "user": {
          "id": "user-123",
          "name": "Test User",
          "avatar": "🧠",
          "totalXp": 2000,
          "currentLevel": 6,
          "currentStreak": 13,
          "longestStreak": 25,
          "lastXpDate": "2026-03-07"
        },
        "settings": {
          "theme": "dark",
          "language": "es",
          "notifications": true
        }
      }
    },
    {
      "id": "adyxito",
      "pinHash": "$2a$10$qDwa8NplsAzT/ayPuLi1BOCZuqeCHt3O77We/N4iLAa7.Q4hIupOW",
      "state": null
    },
    {
      "id": "testaccount123",
      "pinHash": "$2a$10$xl7U2hcwtEbnPfov0EHFlOyuHtHXpbpln3hoUGP1k7uQgLFg.54jW",
      "state": null
    },
    {
      "id": "frontend-test",
      "pinHash": "$2a$10$qfuKRhNvd.K1nGt.H9Nd3u/j8zjaTREFQwyjo.DVKxa7xC.XoIjFa",
      "state": {}
    },
    {
      "id": "test",
      "pinHash": "$2a$10$NuM6pCiYOowuITjVELxiN.u.Ei5XlsTa2L/866MgFc6n.tuHhVPua",
      "state": null
    },
    {
      "id": "andry",
      "pinHash": "$2a$10$nenI7cKSCFeen3Kbpmzde.rhKJoYI6qDjaCs4e42xS0mwFglp/BFy",
      "state": {
        "skills": {
          "categories": [
            {
              "id": "intellect",
              "name": "Intelecto & Ciencia",
              "icon": "Brain",
              "color": "hsl(185, 100%, 50%)",
              "level": 0,
              "children": [
                {
                  "id": "physics",
                  "name": "Fisica",
                  "level": 0,
                  "xpRequired": 1000,
                  "xpCurrent": 0,
                  "children": [],
                  "parentId": null
                },
                {
                  "id": "math",
                  "name": "Matematicas",
                  "level": 0,
                  "xpRequired": 1000,
                  "xpCurrent": 0,
                  "children": [],
                  "parentId": null
                },
                {
                  "id": "programming",
                  "name": "Programacion",
                  "level": 0,
                  "xpRequired": 1000,
                  "xpCurrent": 0,
                  "parentId": null,
                  "children": [
                    {
                      "id": "frontend",
                      "name": "Frontend",
                      "level": 0,
                      "xpRequired": 1000,
                      "xpCurrent": 0,
                      "children": [],
                      "parentId": "programming"
                    },
                    {
                      "id": "backend",
                      "name": "Backend",
                      "level": 0,
                      "xpRequired": 1000,
                      "xpCurrent": 0,
                      "children": [],
                      "parentId": "programming"
                    },
                    {
                      "id": "devops",
                      "name": "DevOps",
                      "level": 0,
                      "xpRequired": 1000,
                      "xpCurrent": 0,
                      "children": [],
                      "parentId": "programming"
                    }
                  ]
                },
                {
                  "id": "networking",
                  "name": "Redes",
                  "level": 0,
                  "xpRequired": 1000,
                  "xpCurrent": 0,
                  "children": [],
                  "parentId": null
                },
                {
                  "id": "ai",
                  "name": "IA & ML",
                  "level": 0,
                  "xpRequired": 1000,
                  "xpCurrent": 0,
                  "children": [],
                  "parentId": null
                }
              ]
            },
            {
              "id": "wellness",
              "name": "Bienestar & Salud",
              "icon": "Heart",
              "color": "hsl(300, 100%, 50%)",
              "level": 0,
              "children": [
                {
                  "id": "health",
                  "name": "Salud General",
                  "level": 0,
                  "xpRequired": 1000,
                  "xpCurrent": 0,
                  "children": [],
                  "parentId": null
                },
                {
                  "id": "exercise",
                  "name": "Ejercicio",
                  "level": 0,
                  "xpRequired": 1000,
                  "xpCurrent": 0,
                  "children": [],
                  "parentId": null
                },
                {
                  "id": "nutrition",
                  "name": "Nutricion",
                  "level": 0,
                  "xpRequired": 1000,
                  "xpCurrent": 0,
                  "children": [],
                  "parentId": null
                },
                {
                  "id": "meditation",
                  "name": "Meditacion",
                  "level": 0,
                  "xpRequired": 1000,
                  "xpCurrent": 0,
                  "children": [],
                  "parentId": null
                },
                {
                  "id": "sleep",
                  "name": "Sueno",
                  "level": 0,
                  "xpRequired": 1000,
                  "xpCurrent": 0,
                  "children": [],
                  "parentId": null
                }
              ]
            },
            {
              "id": "humanities",
              "name": "Humanidades & Sociedad",
              "icon": "BookOpen",
              "color": "hsl(82, 100%, 55%)",
              "level": 0,
              "children": [
                {
                  "id": "sociology",
                  "name": "Sociologia",
                  "level": 0,
                  "xpRequired": 1000,
                  "xpCurrent": 0,
                  "children": [],
                  "parentId": null
                },
                {
                  "id": "history",
                  "name": "Historia",
                  "level": 0,
                  "xpRequired": 1000,
                  "xpCurrent": 0,
                  "children": [],
                  "parentId": null
                },
                {
                  "id": "philosophy",
                  "name": "Filosofia",
                  "level": 0,
                  "xpRequired": 1000,
                  "xpCurrent": 0,
                  "children": [],
                  "parentId": null
                },
                {
                  "id": "languages",
                  "name": "Bilingue",
                  "level": 0,
                  "xpRequired": 1000,
                  "xpCurrent": 0,
                  "children": [],
                  "parentId": null
                },
                {
                  "id": "communication",
                  "name": "Comunicacion",
                  "level": 0,
                  "xpRequired": 1000,
                  "xpCurrent": 0,
                  "children": [],
                  "parentId": null
                }
              ]
            },
            {
              "id": "creativity",
              "name": "Creatividad & Arte",
              "icon": "Palette",
              "color": "hsl(35, 100%, 55%)",
              "level": 1,
              "children": [
                {
                  "id": "visual-art",
                  "name": "Arte Visual",
                  "level": 2,
                  "xpRequired": 1000,
                  "xpCurrent": 15,
                  "children": [],
                  "parentId": null
                },
                {
                  "id": "music",
                  "name": "Musica",
                  "level": 0,
                  "xpRequired": 1000,
                  "xpCurrent": 0,
                  "children": [],
                  "parentId": null
                },
                {
                  "id": "design",
                  "name": "Diseno",
                  "level": 0,
                  "xpRequired": 1000,
                  "xpCurrent": 0,
                  "children": [],
                  "parentId": null
                },
                {
                  "id": "writing",
                  "name": "Escritura",
                  "level": 0,
                  "xpRequired": 1000,
                  "xpCurrent": 0,
                  "children": [],
                  "parentId": null
                }
              ]
            },
            {
              "id": "personal",
              "name": "Desarrollo Personal",
              "icon": "Target",
              "color": "hsl(55, 100%, 55%)",
              "level": 0,
              "children": [
                {
                  "id": "responsibility",
                  "name": "Responsabilidad",
                  "level": 0,
                  "xpRequired": 1000,
                  "xpCurrent": 0,
                  "children": [],
                  "parentId": null
                },
                {
                  "id": "discipline",
                  "name": "Disciplina",
                  "level": 0,
                  "xpRequired": 1000,
                  "xpCurrent": 0,
                  "children": [],
                  "parentId": null
                },
                {
                  "id": "productivity",
                  "name": "Productividad",
                  "level": 0,
                  "xpRequired": 1000,
                  "xpCurrent": 0,
                  "children": [],
                  "parentId": null
                },
                {
                  "id": "leadership",
                  "name": "Liderazgo",
                  "level": 0,
                  "xpRequired": 1000,
                  "xpCurrent": 0,
                  "children": [],
                  "parentId": null
                }
              ]
            },
            {
              "id": "finance",
              "name": "Finanzas & Exito",
              "icon": "TrendingUp",
              "color": "hsl(220, 100%, 60%)",
              "level": 0,
              "children": [
                {
                  "id": "savings",
                  "name": "Ahorro",
                  "level": 0,
                  "xpRequired": 1000,
                  "xpCurrent": 0,
                  "children": [],
                  "parentId": null
                },
                {
                  "id": "investments",
                  "name": "Inversiones",
                  "level": 0,
                  "xpRequired": 1000,
                  "xpCurrent": 0,
                  "children": [],
                  "parentId": null
                },
                {
                  "id": "business",
                  "name": "Negocios",
                  "level": 0,
                  "xpRequired": 1000,
                  "xpCurrent": 0,
                  "children": [],
                  "parentId": null
                },
                {
                  "id": "income",
                  "name": "Ingresos",
                  "level": 0,
                  "xpRequired": 1000,
                  "xpCurrent": 0,
                  "children": [],
                  "parentId": null
                }
              ]
            }
          ],
          "overallLevel": 0
        },
        "tasks": [
          {
            "id": "c475a5f9-462c-44c8-9d29-1d96d2047768",
            "description": "",
            "frequency": "daily",
            "priority": "medium",
            "status": "completed",
            "validationRule": "manual-confirm",
            "xpReward": 15,
            "createdAt": "2026-03-08T05:10:54.292Z",
            "tags": [],
            "streak": 1,
            "title": "Pintar ",
            "skillCategoryId": "creativity",
            "subSkillId": "visual-art",
            "completedAt": "2026-03-08T05:10:56.049Z"
          }
        ],
        "goals": [],
        "user": {
          "id": "user-1",
          "nickname": "CyberRunner",
          "avatarUrl": null,
          "level": 1,
          "totalXp": 15,
          "joinedAt": "2026-01-01T00:00:00.000Z",
          "currentStreak": 1,
          "longestStreak": 1
        },
        "settings": {
          "theme": "cyberpunk",
          "notificationsEnabled": true,
          "dailyReminderTime": "08:00",
          "strictValidation": true,
          "language": "es"
        }
      }
    }
  ]
}